aps_common_toolkit/__init__.py
aps_common_toolkit/py.typed
aps_common_toolkit/models/__init__.py
aps_common_toolkit/models/auth.py
aps_common_toolkit/models/base.py
aps_common_toolkit/services/__init__.py
aps_common_toolkit/services/auth.py
aps_common_toolkit/services/db.py
aps_common_toolkit/utils/__init__.py
aps_common_toolkit/utils/security.py
aps_common_toolkit-2.1.0.dist-info/METADATA
aps_common_toolkit-2.1.0.dist-info/WHEEL
aps_common_toolkit-2.1.0.dist-info/top_level.txt
aps_common_toolkit-2.1.0.dist-info/RECORD
