Metadata-Version: 2.4
Name: aps_common_toolkit
Version: 2.1.0
Summary: Common services and utilities used across projects
Author: Abhay Pratap Singh
Requires-Python: >=3.12
Requires-Dist: argon2-cffi==25.1.0
Requires-Dist: SQLAlchemy==2.0.43
Requires-Dist: PyJWT==2.10.1
Dynamic: author
Dynamic: requires-dist
Dynamic: requires-python
Dynamic: summary
